{
  "date": "2026-06-17",
  "markets": [
    {
      "pitcher_id": 418,
      "pitcher_name": "George Kirby",
      "pitcher_team": "Seattle Mariners",
      "book": "kalshi",
      "line": 3.5,
      "threshold": 4,
      "predicted_mu": 5.06,
      "p_yes": 0.7264,
      "p_no": 0.2736,
      "ev_yes": -0.1603,
      "ev_no": 1.0275,
      "edge_yes": -0.1387,
      "edge_no": 0.1387,
      "kelly_yes": null,
      "kelly_no": 5.0,
      "over_odds": -641,
      "under_odds": 641,
      "best_side": "NO",
      "best_ev": 1.0275,
      "best_edge": 0.1387,
      "best_odds": 641,
      "best_p": 0.2736,
      "best_kelly_pct": 5.0,
      "flagged": true
    },
    {
      "pitcher_id": 4941190,
      "pitcher_name": "JR Ritchie",
      "pitcher_team": "Atlanta Braves",
      "book": "kalshi",
      "line": 6.5,
      "threshold": 7,
      "predicted_mu": 4.42,
      "p_yes": 0.1689,
      "p_no": 0.8311,
      "ev_yes": 0.8766,
      "ev_no": -0.0867,
      "edge_yes": 0.0789,
      "edge_no": -0.0789,
      "kelly_yes": 4.34,
      "kelly_no": null,
      "over_odds": 1011,
      "under_odds": -1011,
      "best_side": "YES",
      "best_ev": 0.8766,
      "best_edge": 0.0789,
      "best_odds": 1011,
      "best_p": 0.1689,
      "best_kelly_pct": 4.34,
      "flagged": true
    },
    {
      "pitcher_id": 418,
      "pitcher_name": "George Kirby",
      "pitcher_team": "Seattle Mariners",
      "book": "kalshi",
      "line": 4.5,
      "threshold": 5,
      "predicted_mu": 5.06,
      "p_yes": 0.5587,
      "p_no": 0.4413,
      "ev_yes": -0.2599,
      "ev_no": 0.8004,
      "edge_yes": -0.1962,
      "edge_no": 0.1962,
      "kelly_yes": null,
      "kelly_no": 5.0,
      "over_odds": -308,
      "under_odds": 308,
      "best_side": "NO",
      "best_ev": 0.8004,
      "best_edge": 0.1962,
      "best_odds": 308,
      "best_p": 0.4413,
      "best_kelly_pct": 5.0,
      "flagged": true
    },
    {
      "pitcher_id": 656,
      "pitcher_name": "Javier Assad",
      "pitcher_team": "Chicago Cubs",
      "book": "kalshi",
      "line": 2.5,
      "threshold": 3,
      "predicted_mu": 3.11,
      "p_yes": 0.593,
      "p_no": 0.407,
      "ev_yes": -0.23,
      "ev_no": 0.7707,
      "edge_yes": -0.1772,
      "edge_no": 0.1772,
      "kelly_yes": null,
      "kelly_no": 5.0,
      "over_odds": -335,
      "under_odds": 335,
      "best_side": "NO",
      "best_ev": 0.7707,
      "best_edge": 0.1772,
      "best_odds": 335,
      "best_p": 0.407,
      "best_kelly_pct": 5.0,
      "flagged": true
    },
    {
      "pitcher_id": 656,
      "pitcher_name": "Javier Assad",
      "pitcher_team": "Chicago Cubs",
      "book": "kalshi",
      "line": 1.5,
      "threshold": 2,
      "predicted_mu": 3.11,
      "p_yes": 0.8064,
      "p_no": 0.1936,
      "ev_yes": -0.094,
      "ev_no": 0.7603,
      "edge_yes": -0.0836,
      "edge_no": 0.0836,
      "kelly_yes": null,
      "kelly_no": 4.7,
      "over_odds": -809,
      "under_odds": 809,
      "best_side": "NO",
      "best_ev": 0.7603,
      "best_edge": 0.0836,
      "best_odds": 809,
      "best_p": 0.1936,
      "best_kelly_pct": 4.7,
      "flagged": true
    },
    {
      "pitcher_id": 543,
      "pitcher_name": "Braxton Ashcraft",
      "pitcher_team": "Pittsburgh Pirates",
      "book": "kalshi",
      "line": 8.5,
      "threshold": 9,
      "predicted_mu": 5.66,
      "p_yes": 0.1335,
      "p_no": 0.8665,
      "ev_yes": 0.6683,
      "ev_no": -0.0581,
      "edge_yes": 0.0535,
      "edge_no": -0.0535,
      "kelly_yes": 2.91,
      "kelly_no": null,
      "over_odds": 1150,
      "under_odds": -1150,
      "best_side": "YES",
      "best_ev": 0.6683,
      "best_edge": 0.0535,
      "best_odds": 1150,
      "best_p": 0.1335,
      "best_kelly_pct": 2.91,
      "flagged": true
    },
    {
      "pitcher_id": 4941190,
      "pitcher_name": "JR Ritchie",
      "pitcher_team": "Atlanta Braves",
      "book": "kalshi",
      "line": 5.5,
      "threshold": 6,
      "predicted_mu": 4.42,
      "p_yes": 0.2887,
      "p_no": 0.7113,
      "ev_yes": 0.6049,
      "ev_no": -0.1327,
      "edge_yes": 0.1088,
      "edge_no": -0.1088,
      "kelly_yes": 5.0,
      "kelly_no": null,
      "over_odds": 456,
      "under_odds": -456,
      "best_side": "YES",
      "best_ev": 0.6049,
      "best_edge": 0.1088,
      "best_odds": 456,
      "best_p": 0.2887,
      "best_kelly_pct": 5.0,
      "flagged": true
    },
    {
      "pitcher_id": 4787743,
      "pitcher_name": "Jake Bennett",
      "pitcher_team": "Boston Red Sox",
      "book": "kalshi",
      "line": 5.5,
      "threshold": 6,
      "predicted_mu": 3.43,
      "p_yes": 0.1414,
      "p_no": 0.8586,
      "ev_yes": 0.5714,
      "ev_no": -0.0565,
      "edge_yes": 0.0514,
      "edge_no": -0.0514,
      "kelly_yes": 2.83,
      "kelly_no": null,
      "over_odds": 1011,
      "under_odds": -1011,
      "best_side": "YES",
      "best_ev": 0.5714,
      "best_edge": 0.0514,
      "best_odds": 1011,
      "best_p": 0.1414,
      "best_kelly_pct": 2.83,
      "flagged": true
    },
    {
      "pitcher_id": 879,
      "pitcher_name": "Gavin Williams",
      "pitcher_team": "Cleveland Guardians",
      "book": "kalshi",
      "line": 10.5,
      "threshold": 11,
      "predicted_mu": 6.54,
      "p_yes": 0.0837,
      "p_no": 0.9163,
      "ev_yes": 0.5212,
      "ev_no": -0.0303,
      "edge_yes": 0.0287,
      "edge_no": -0.0287,
      "kelly_yes": 1.52,
      "kelly_no": null,
      "over_odds": 1718,
      "under_odds": -1718,
      "best_side": "YES",
      "best_ev": 0.5212,
      "best_edge": 0.0287,
      "best_odds": 1718,
      "best_p": 0.0837,
      "best_kelly_pct": 1.52,
      "flagged": true
    },
    {
      "pitcher_id": 418,
      "pitcher_name": "George Kirby",
      "pitcher_team": "Seattle Mariners",
      "book": "kalshi",
      "line": 5.5,
      "threshold": 6,
      "predicted_mu": 5.06,
      "p_yes": 0.3931,
      "p_no": 0.6069,
      "ev_yes": -0.3449,
      "ev_no": 0.5173,
      "edge_yes": -0.2069,
      "edge_no": 0.2069,
      "kelly_yes": null,
      "kelly_no": 5.0,
      "over_odds": -150,
      "under_odds": 150,
      "best_side": "NO",
      "best_ev": 0.5173,
      "best_edge": 0.2069,
      "best_odds": 150,
      "best_p": 0.6069,
      "best_kelly_pct": 5.0,
      "flagged": true
    },
    {
      "pitcher_id": 656,
      "pitcher_name": "Javier Assad",
      "pitcher_team": "Chicago Cubs",
      "book": "kalshi",
      "line": 3.5,
      "threshold": 4,
      "predicted_mu": 3.11,
      "p_yes": 0.3771,
      "p_no": 0.6229,
      "ev_yes": -0.3497,
      "ev_no": 0.4826,
      "edge_yes": -0.2028,
      "edge_no": 0.2028,
      "kelly_yes": null,
      "kelly_no": 5.0,
      "over_odds": -138,
      "under_odds": 138,
      "best_side": "NO",
      "best_ev": 0.4826,
      "best_edge": 0.2028,
      "best_odds": 138,
      "best_p": 0.6229,
      "best_kelly_pct": 5.0,
      "flagged": true
    },
    {
      "pitcher_id": 6032,
      "pitcher_name": "Anthony Kay",
      "pitcher_team": "Chicago White Sox",
      "book": "kalshi",
      "line": 2.5,
      "threshold": 3,
      "predicted_mu": 4.16,
      "p_yes": 0.7708,
      "p_no": 0.2292,
      "ev_yes": -0.0768,
      "ev_no": 0.3888,
      "edge_yes": -0.0642,
      "edge_no": 0.0642,
      "kelly_yes": null,
      "kelly_no": 3.84,
      "over_odds": -506,
      "under_odds": 506,
      "best_side": "NO",
      "best_ev": 0.3888,
      "best_edge": 0.0642,
      "best_odds": 506,
      "best_p": 0.2292,
      "best_kelly_pct": 3.84,
      "flagged": true
    },
    {
      "pitcher_id": 1055,
      "pitcher_name": "Aaron Civale",
      "pitcher_team": "Oakland Athletics",
      "book": "kalshi",
      "line": 6.5,
      "threshold": 7,
      "predicted_mu": 3.7,
      "p_yes": 0.0903,
      "p_no": 0.9097,
      "ev_yes": 0.3884,
      "ev_no": -0.027,
      "edge_yes": 0.0253,
      "edge_no": -0.0253,
      "kelly_yes": 1.35,
      "kelly_no": null,
      "over_odds": 1438,
      "under_odds": -1438,
      "best_side": "YES",
      "best_ev": 0.3884,
      "best_edge": 0.0253,
      "best_odds": 1438,
      "best_p": 0.0903,
      "best_kelly_pct": 1.35,
      "flagged": true
    },
    {
      "pitcher_id": 879,
      "pitcher_name": "Gavin Williams",
      "pitcher_team": "Cleveland Guardians",
      "book": "kalshi",
      "line": 9.5,
      "threshold": 10,
      "predicted_mu": 6.54,
      "p_yes": 0.1414,
      "p_no": 0.8586,
      "ev_yes": 0.3463,
      "ev_no": -0.0407,
      "edge_yes": 0.0364,
      "edge_no": -0.0364,
      "kelly_yes": 2.03,
      "kelly_no": null,
      "over_odds": 852,
      "under_odds": -852,
      "best_side": "YES",
      "best_ev": 0.3463,
      "best_edge": 0.0364,
      "best_odds": 852,
      "best_p": 0.1414,
      "best_kelly_pct": 2.03,
      "flagged": true
    },
    {
      "pitcher_id": 4941190,
      "pitcher_name": "JR Ritchie",
      "pitcher_team": "Atlanta Braves",
      "book": "kalshi",
      "line": 4.5,
      "threshold": 5,
      "predicted_mu": 4.42,
      "p_yes": 0.4491,
      "p_no": 0.5509,
      "ev_yes": 0.3203,
      "ev_no": -0.1651,
      "edge_yes": 0.1089,
      "edge_no": -0.1089,
      "kelly_yes": 5.0,
      "kelly_no": null,
      "over_odds": 194,
      "under_odds": -194,
      "best_side": "YES",
      "best_ev": 0.3203,
      "best_edge": 0.1089,
      "best_odds": 194,
      "best_p": 0.4491,
      "best_kelly_pct": 5.0,
      "flagged": true
    },
    {
      "pitcher_id": 1055,
      "pitcher_name": "Aaron Civale",
      "pitcher_team": "Oakland Athletics",
      "book": "kalshi",
      "line": 5.5,
      "threshold": 6,
      "predicted_mu": 3.7,
      "p_yes": 0.1774,
      "p_no": 0.8226,
      "ev_yes": 0.3145,
      "ev_no": -0.0491,
      "edge_yes": 0.0424,
      "edge_no": -0.0424,
      "kelly_yes": 2.45,
      "kelly_no": null,
      "over_odds": 641,
      "under_odds": -641,
      "best_side": "YES",
      "best_ev": 0.3145,
      "best_edge": 0.0424,
      "best_odds": 641,
      "best_p": 0.1774,
      "best_kelly_pct": 2.45,
      "flagged": true
    },
    {
      "pitcher_id": 418,
      "pitcher_name": "George Kirby",
      "pitcher_team": "Seattle Mariners",
      "book": "kalshi",
      "line": 6.5,
      "threshold": 7,
      "predicted_mu": 5.06,
      "p_yes": 0.2536,
      "p_no": 0.7464,
      "ev_yes": -0.4039,
      "ev_no": 0.2992,
      "edge_yes": -0.1719,
      "edge_no": 0.1719,
      "kelly_yes": null,
      "kelly_no": 5.0,
      "over_odds": 135,
      "under_odds": -135,
      "best_side": "NO",
      "best_ev": 0.2992,
      "best_edge": 0.1719,
      "best_odds": -135,
      "best_p": 0.7464,
      "best_kelly_pct": 5.0,
      "flagged": true
    },
    {
      "pitcher_id": 1490,
      "pitcher_name": "Kyle Bradish",
      "pitcher_team": "Baltimore Orioles",
      "book": "kalshi",
      "line": 3.5,
      "threshold": 4,
      "predicted_mu": 5.22,
      "p_yes": 0.7472,
      "p_no": 0.2528,
      "ev_yes": -0.0719,
      "ev_no": 0.297,
      "edge_yes": -0.0579,
      "edge_no": 0.0579,
      "kelly_yes": null,
      "kelly_no": 3.6,
      "over_odds": -413,
      "under_odds": 413,
      "best_side": "NO",
      "best_ev": 0.297,
      "best_edge": 0.0579,
      "best_odds": 413,
      "best_p": 0.2528,
      "best_kelly_pct": 3.6,
      "flagged": true
    },
    {
      "pitcher_id": 1490,
      "pitcher_name": "Kyle Bradish",
      "pitcher_team": "Baltimore Orioles",
      "book": "kalshi",
      "line": 2.5,
      "threshold": 3,
      "predicted_mu": 5.22,
      "p_yes": 0.8779,
      "p_no": 0.1221,
      "ev_yes": -0.03,
      "ev_no": 0.2858,
      "edge_yes": -0.0271,
      "edge_no": 0.0271,
      "kelly_yes": null,
      "kelly_no": 1.5,
      "over_odds": -953,
      "under_odds": 953,
      "best_side": "NO",
      "best_ev": 0.2858,
      "best_edge": 0.0271,
      "best_odds": 953,
      "best_p": 0.1221,
      "best_kelly_pct": 1.5,
      "flagged": true
    },
    {
      "pitcher_id": 3315628,
      "pitcher_name": "Brandon Sproat",
      "pitcher_team": "Milwaukee Brewers",
      "book": "kalshi",
      "line": 2.5,
      "threshold": 3,
      "predicted_mu": 4.47,
      "p_yes": 0.8078,
      "p_no": 0.1922,
      "ev_yes": -0.0497,
      "ev_no": 0.2819,
      "edge_yes": -0.0423,
      "edge_no": 0.0423,
      "kelly_yes": null,
      "kelly_no": 2.49,
      "over_odds": -567,
      "under_odds": 567,
      "best_side": "NO",
      "best_ev": 0.2819,
      "best_edge": 0.0423,
      "best_odds": 567,
      "best_p": 0.1922,
      "best_kelly_pct": 2.49,
      "flagged": true
    },
    {
      "pitcher_id": 656,
      "pitcher_name": "Javier Assad",
      "pitcher_team": "Chicago Cubs",
      "book": "kalshi",
      "line": 4.5,
      "threshold": 5,
      "predicted_mu": 3.11,
      "p_yes": 0.2095,
      "p_no": 0.7905,
      "ev_yes": -0.4261,
      "ev_no": 0.2449,
      "edge_yes": -0.1555,
      "edge_no": 0.1555,
      "kelly_yes": null,
      "kelly_no": 5.0,
      "over_odds": 174,
      "under_odds": -174,
      "best_side": "NO",
      "best_ev": 0.2449,
      "best_edge": 0.1555,
      "best_odds": -174,
      "best_p": 0.7905,
      "best_kelly_pct": 5.0,
      "flagged": true
    },
    {
      "pitcher_id": 4787743,
      "pitcher_name": "Jake Bennett",
      "pitcher_team": "Boston Red Sox",
      "book": "kalshi",
      "line": 4.5,
      "threshold": 5,
      "predicted_mu": 3.43,
      "p_yes": 0.2659,
      "p_no": 0.7341,
      "ev_yes": 0.2365,
      "ev_no": -0.0648,
      "edge_yes": 0.0509,
      "edge_no": -0.0509,
      "kelly_yes": 3.24,
      "kelly_no": null,
      "over_odds": 365,
      "under_odds": -365,
      "best_side": "YES",
      "best_ev": 0.2365,
      "best_edge": 0.0509,
      "best_odds": 365,
      "best_p": 0.2659,
      "best_kelly_pct": 3.24,
      "flagged": true
    },
    {
      "pitcher_id": 6032,
      "pitcher_name": "Anthony Kay",
      "pitcher_team": "Chicago White Sox",
      "book": "kalshi",
      "line": 3.5,
      "threshold": 4,
      "predicted_mu": 4.16,
      "p_yes": 0.5875,
      "p_no": 0.4125,
      "ev_yes": -0.1173,
      "ev_no": 0.2334,
      "edge_yes": -0.0781,
      "edge_no": 0.0781,
      "kelly_yes": null,
      "kelly_no": 5.0,
      "over_odds": -199,
      "under_odds": 199,
      "best_side": "NO",
      "best_ev": 0.2334,
      "best_edge": 0.0781,
      "best_odds": 199,
      "best_p": 0.4125,
      "best_kelly_pct": 5.0,
      "flagged": true
    },
    {
      "pitcher_id": 4787743,
      "pitcher_name": "Jake Bennett",
      "pitcher_team": "Boston Red Sox",
      "book": "kalshi",
      "line": 6.5,
      "threshold": 7,
      "predicted_mu": 3.43,
      "p_yes": 0.0677,
      "p_no": 0.9323,
      "ev_yes": 0.2315,
      "ev_no": -0.0135,
      "edge_yes": 0.0127,
      "edge_no": -0.0127,
      "kelly_yes": 0.67,
      "kelly_no": null,
      "over_odds": 1718,
      "under_odds": -1718,
      "best_side": "YES",
      "best_ev": 0.2315,
      "best_edge": 0.0127,
      "best_odds": 1718,
      "best_p": 0.0677,
      "best_kelly_pct": 0.67,
      "flagged": true
    },
    {
      "pitcher_id": 3315628,
      "pitcher_name": "Brandon Sproat",
      "pitcher_team": "Milwaukee Brewers",
      "book": "kalshi",
      "line": 3.5,
      "threshold": 4,
      "predicted_mu": 4.47,
      "p_yes": 0.6391,
      "p_no": 0.3609,
      "ev_yes": -0.0935,
      "ev_no": 0.2235,
      "edge_yes": -0.0659,
      "edge_no": 0.0659,
      "kelly_yes": null,
      "kelly_no": 4.67,
      "over_odds": -239,
      "under_odds": 239,
      "best_side": "NO",
      "best_ev": 0.2235,
      "best_edge": 0.0659,
      "best_odds": 239,
      "best_p": 0.3609,
      "best_kelly_pct": 4.67,
      "flagged": true
    },
    {
      "pitcher_id": 543,
      "pitcher_name": "Braxton Ashcraft",
      "pitcher_team": "Pittsburgh Pirates",
      "book": "kalshi",
      "line": 7.5,
      "threshold": 8,
      "predicted_mu": 5.66,
      "p_yes": 0.2218,
      "p_no": 0.7782,
      "ev_yes": 0.1997,
      "ev_no": -0.0453,
      "edge_yes": 0.0369,
      "edge_no": -0.0369,
      "kelly_yes": 2.26,
      "kelly_no": null,
      "over_odds": 441,
      "under_odds": -441,
      "best_side": "YES",
      "best_ev": 0.1997,
      "best_edge": 0.0369,
      "best_odds": 441,
      "best_p": 0.2218,
      "best_kelly_pct": 2.26,
      "flagged": true
    },
    {
      "pitcher_id": 1490,
      "pitcher_name": "Kyle Bradish",
      "pitcher_team": "Baltimore Orioles",
      "book": "kalshi",
      "line": 8.5,
      "threshold": 9,
      "predicted_mu": 5.22,
      "p_yes": 0.0953,
      "p_no": 0.9047,
      "ev_yes": 0.1918,
      "ev_no": -0.0167,
      "edge_yes": 0.0153,
      "edge_no": -0.0153,
      "kelly_yes": 0.83,
      "kelly_no": null,
      "over_odds": 1150,
      "under_odds": -1150,
      "best_side": "YES",
      "best_ev": 0.1918,
      "best_edge": 0.0153,
      "best_odds": 1150,
      "best_p": 0.0953,
      "best_kelly_pct": 0.83,
      "flagged": true
    },
    {
      "pitcher_id": 1490,
      "pitcher_name": "Kyle Bradish",
      "pitcher_team": "Baltimore Orioles",
      "book": "kalshi",
      "line": 4.5,
      "threshold": 5,
      "predicted_mu": 5.22,
      "p_yes": 0.5848,
      "p_no": 0.4152,
      "ev_yes": -0.1008,
      "ev_no": 0.1876,
      "edge_yes": -0.0656,
      "edge_no": 0.0656,
      "kelly_yes": null,
      "kelly_no": 5.0,
      "over_odds": -186,
      "under_odds": 186,
      "best_side": "NO",
      "best_ev": 0.1876,
      "best_edge": 0.0656,
      "best_odds": 186,
      "best_p": 0.4152,
      "best_kelly_pct": 5.0,
      "flagged": true
    },
    {
      "pitcher_id": 1055,
      "pitcher_name": "Aaron Civale",
      "pitcher_team": "Oakland Athletics",
      "book": "kalshi",
      "line": 4.5,
      "threshold": 5,
      "predicted_mu": 3.7,
      "p_yes": 0.3148,
      "p_no": 0.6852,
      "ev_yes": 0.1867,
      "ev_no": -0.0674,
      "edge_yes": 0.0495,
      "edge_no": -0.0495,
      "kelly_yes": 3.37,
      "kelly_no": null,
      "over_odds": 277,
      "under_odds": -277,
      "best_side": "YES",
      "best_ev": 0.1867,
      "best_edge": 0.0495,
      "best_odds": 277,
      "best_p": 0.3148,
      "best_kelly_pct": 3.37,
      "flagged": true
    },
    {
      "pitcher_id": 3315628,
      "pitcher_name": "Brandon Sproat",
      "pitcher_team": "Milwaukee Brewers",
      "book": "kalshi",
      "line": 4.5,
      "threshold": 5,
      "predicted_mu": 4.47,
      "p_yes": 0.4568,
      "p_no": 0.5432,
      "ev_yes": -0.146,
      "ev_no": 0.1679,
      "edge_yes": -0.0781,
      "edge_no": 0.0781,
      "kelly_yes": null,
      "kelly_no": 5.0,
      "over_odds": -115,
      "under_odds": 115,
      "best_side": "NO",
      "best_ev": 0.1679,
      "best_edge": 0.0781,
      "best_odds": 115,
      "best_p": 0.5432,
      "best_kelly_pct": 5.0,
      "flagged": true
    },
    {
      "pitcher_id": 418,
      "pitcher_name": "George Kirby",
      "pitcher_team": "Seattle Mariners",
      "book": "kalshi",
      "line": 7.5,
      "threshold": 8,
      "predicted_mu": 5.06,
      "p_yes": 0.1509,
      "p_no": 0.8491,
      "ev_yes": -0.4417,
      "ev_no": 0.1636,
      "edge_yes": -0.1194,
      "edge_no": 0.1194,
      "kelly_yes": null,
      "kelly_no": 5.0,
      "over_odds": 270,
      "under_odds": -270,
      "best_side": "NO",
      "best_ev": 0.1636,
      "best_edge": 0.1194,
      "best_odds": -270,
      "best_p": 0.8491,
      "best_kelly_pct": 5.0,
      "flagged": true
    },
    {
      "pitcher_id": 4941190,
      "pitcher_name": "JR Ritchie",
      "pitcher_team": "Atlanta Braves",
      "book": "kalshi",
      "line": 3.5,
      "threshold": 4,
      "predicted_mu": 4.42,
      "p_yes": 0.6321,
      "p_no": 0.3679,
      "ev_yes": 0.1502,
      "ev_no": -0.1833,
      "edge_yes": 0.0826,
      "edge_no": -0.0826,
      "kelly_yes": 5.0,
      "kelly_no": null,
      "over_odds": -122,
      "under_odds": 122,
      "best_side": "YES",
      "best_ev": 0.1502,
      "best_edge": 0.0826,
      "best_odds": -122,
      "best_p": 0.6321,
      "best_kelly_pct": 5.0,
      "flagged": true
    },
    {
      "pitcher_id": 879,
      "pitcher_name": "Gavin Williams",
      "pitcher_team": "Cleveland Guardians",
      "book": "kalshi",
      "line": 4.5,
      "threshold": 5,
      "predicted_mu": 6.54,
      "p_yes": 0.7601,
      "p_no": 0.2399,
      "ev_yes": -0.0378,
      "ev_no": 0.142,
      "edge_yes": -0.0298,
      "edge_no": 0.0298,
      "kelly_yes": null,
      "kelly_no": 1.89,
      "over_odds": -376,
      "under_odds": 376,
      "best_side": "NO",
      "best_ev": 0.142,
      "best_edge": 0.0298,
      "best_odds": 376,
      "best_p": 0.2399,
      "best_kelly_pct": 1.89,
      "flagged": true
    },
    {
      "pitcher_id": 4787743,
      "pitcher_name": "Jake Bennett",
      "pitcher_team": "Boston Red Sox",
      "book": "kalshi",
      "line": 3.5,
      "threshold": 4,
      "predicted_mu": 3.43,
      "p_yes": 0.445,
      "p_no": 0.555,
      "ev_yes": 0.1391,
      "ev_no": -0.0892,
      "edge_yes": 0.0543,
      "edge_no": -0.0543,
      "kelly_yes": 4.46,
      "kelly_no": null,
      "over_odds": 156,
      "under_odds": -156,
      "best_side": "YES",
      "best_ev": 0.1391,
      "best_edge": 0.0543,
      "best_odds": 156,
      "best_p": 0.445,
      "best_kelly_pct": 4.46,
      "flagged": true
    },
    {
      "pitcher_id": 6032,
      "pitcher_name": "Anthony Kay",
      "pitcher_team": "Chicago White Sox",
      "book": "kalshi",
      "line": 4.5,
      "threshold": 5,
      "predicted_mu": 4.16,
      "p_yes": 0.4015,
      "p_no": 0.5985,
      "ev_yes": -0.1528,
      "ev_no": 0.1377,
      "edge_yes": -0.0724,
      "edge_no": 0.0724,
      "kelly_yes": null,
      "kelly_no": 5.0,
      "over_odds": 111,
      "under_odds": -111,
      "best_side": "NO",
      "best_ev": 0.1377,
      "best_edge": 0.0724,
      "best_odds": -111,
      "best_p": 0.5985,
      "best_kelly_pct": 5.0,
      "flagged": true
    },
    {
      "pitcher_id": 656,
      "pitcher_name": "Javier Assad",
      "pitcher_team": "Chicago Cubs",
      "book": "kalshi",
      "line": 5.5,
      "threshold": 6,
      "predicted_mu": 3.11,
      "p_yes": 0.103,
      "p_no": 0.897,
      "ev_yes": -0.4714,
      "ev_no": 0.1141,
      "edge_yes": -0.0919,
      "edge_no": 0.0919,
      "kelly_yes": null,
      "kelly_no": 5.0,
      "over_odds": 413,
      "under_odds": -413,
      "best_side": "NO",
      "best_ev": 0.1141,
      "best_edge": 0.0919,
      "best_odds": -413,
      "best_p": 0.897,
      "best_kelly_pct": 5.0,
      "flagged": true
    },
    {
      "pitcher_id": 3315628,
      "pitcher_name": "Brandon Sproat",
      "pitcher_team": "Milwaukee Brewers",
      "book": "kalshi",
      "line": 1.5,
      "threshold": 2,
      "predicted_mu": 4.47,
      "p_yes": 0.9276,
      "p_no": 0.0724,
      "ev_yes": -0.0079,
      "ev_no": 0.1138,
      "edge_yes": -0.0074,
      "edge_no": 0.0074,
      "kelly_yes": null,
      "kelly_no": 0.4,
      "over_odds": -1438,
      "under_odds": 1438,
      "best_side": "NO",
      "best_ev": 0.1138,
      "best_edge": 0.0074,
      "best_odds": 1438,
      "best_p": 0.0724,
      "best_kelly_pct": 0.4,
      "flagged": true
    },
    {
      "pitcher_id": 543,
      "pitcher_name": "Braxton Ashcraft",
      "pitcher_team": "Pittsburgh Pirates",
      "book": "kalshi",
      "line": 6.5,
      "threshold": 7,
      "predicted_mu": 5.66,
      "p_yes": 0.343,
      "p_no": 0.657,
      "ev_yes": 0.108,
      "ev_no": -0.0484,
      "edge_yes": 0.0334,
      "edge_no": -0.0334,
      "kelly_yes": 2.42,
      "kelly_no": null,
      "over_odds": 223,
      "under_odds": -223,
      "best_side": "YES",
      "best_ev": 0.108,
      "best_edge": 0.0334,
      "best_odds": 223,
      "best_p": 0.343,
      "best_kelly_pct": 2.42,
      "flagged": true
    },
    {
      "pitcher_id": 879,
      "pitcher_name": "Gavin Williams",
      "pitcher_team": "Cleveland Guardians",
      "book": "kalshi",
      "line": 3.5,
      "threshold": 4,
      "predicted_mu": 6.54,
      "p_yes": 0.8727,
      "p_no": 0.1273,
      "ev_yes": -0.014,
      "ev_no": 0.1079,
      "edge_yes": -0.0124,
      "edge_no": 0.0124,
      "kelly_yes": null,
      "kelly_no": 0.7,
      "over_odds": -770,
      "under_odds": 770,
      "best_side": "NO",
      "best_ev": 0.1079,
      "best_edge": 0.0124,
      "best_odds": 770,
      "best_p": 0.1273,
      "best_kelly_pct": 0.7,
      "flagged": true
    },
    {
      "pitcher_id": 879,
      "pitcher_name": "Gavin Williams",
      "pitcher_team": "Cleveland Guardians",
      "book": "kalshi",
      "line": 5.5,
      "threshold": 6,
      "predicted_mu": 6.54,
      "p_yes": 0.6206,
      "p_no": 0.3794,
      "ev_yes": -0.0527,
      "ev_no": 0.1002,
      "edge_yes": -0.0345,
      "edge_no": 0.0345,
      "kelly_yes": null,
      "kelly_no": 2.64,
      "over_odds": -190,
      "under_odds": 190,
      "best_side": "NO",
      "best_ev": 0.1002,
      "best_edge": 0.0345,
      "best_odds": 190,
      "best_p": 0.3794,
      "best_kelly_pct": 2.64,
      "flagged": true
    },
    {
      "pitcher_id": 879,
      "pitcher_name": "Gavin Williams",
      "pitcher_team": "Cleveland Guardians",
      "book": "kalshi",
      "line": 8.5,
      "threshold": 9,
      "predicted_mu": 6.54,
      "p_yes": 0.2254,
      "p_no": 0.7746,
      "ev_yes": 0.1,
      "ev_no": -0.0258,
      "edge_yes": 0.0205,
      "edge_no": -0.0205,
      "kelly_yes": 1.29,
      "kelly_no": null,
      "over_odds": 388,
      "under_odds": -388,
      "best_side": "YES",
      "best_ev": 0.1,
      "best_edge": 0.0205,
      "best_odds": 388,
      "best_p": 0.2254,
      "best_kelly_pct": 1.29,
      "flagged": true
    },
    {
      "pitcher_id": 1055,
      "pitcher_name": "Aaron Civale",
      "pitcher_team": "Oakland Athletics",
      "book": "kalshi",
      "line": 3.5,
      "threshold": 4,
      "predicted_mu": 3.7,
      "p_yes": 0.4993,
      "p_no": 0.5007,
      "ev_yes": 0.0984,
      "ev_no": -0.082,
      "edge_yes": 0.0447,
      "edge_no": -0.0447,
      "kelly_yes": 4.1,
      "kelly_no": null,
      "over_odds": 120,
      "under_odds": -120,
      "best_side": "YES",
      "best_ev": 0.0984,
      "best_edge": 0.0447,
      "best_odds": 120,
      "best_p": 0.4993,
      "best_kelly_pct": 4.1,
      "flagged": true
    },
    {
      "pitcher_id": 543,
      "pitcher_name": "Braxton Ashcraft",
      "pitcher_team": "Pittsburgh Pirates",
      "book": "kalshi",
      "line": 3.5,
      "threshold": 4,
      "predicted_mu": 5.66,
      "p_yes": 0.798,
      "p_no": 0.202,
      "ev_yes": -0.021,
      "ev_no": 0.0928,
      "edge_yes": -0.0172,
      "edge_no": 0.0172,
      "kelly_yes": null,
      "kelly_no": 1.05,
      "over_odds": -441,
      "under_odds": 441,
      "best_side": "NO",
      "best_ev": 0.0928,
      "best_edge": 0.0172,
      "best_odds": 441,
      "best_p": 0.202,
      "best_kelly_pct": 1.05,
      "flagged": true
    },
    {
      "pitcher_id": 3315628,
      "pitcher_name": "Brandon Sproat",
      "pitcher_team": "Milwaukee Brewers",
      "book": "kalshi",
      "line": 5.5,
      "threshold": 6,
      "predicted_mu": 4.47,
      "p_yes": 0.2956,
      "p_no": 0.7044,
      "ev_yes": -0.1665,
      "ev_no": 0.0915,
      "edge_yes": -0.059,
      "edge_no": 0.059,
      "kelly_yes": null,
      "kelly_no": 5.0,
      "over_odds": 182,
      "under_odds": -182,
      "best_side": "NO",
      "best_ev": 0.0915,
      "best_edge": 0.059,
      "best_odds": -182,
      "best_p": 0.7044,
      "best_kelly_pct": 5.0,
      "flagged": true
    },
    {
      "pitcher_id": 6032,
      "pitcher_name": "Anthony Kay",
      "pitcher_team": "Chicago White Sox",
      "book": "kalshi",
      "line": 7.5,
      "threshold": 8,
      "predicted_mu": 4.16,
      "p_yes": 0.0706,
      "p_no": 0.9294,
      "ev_yes": 0.0864,
      "ev_no": -0.006,
      "edge_yes": 0.0056,
      "edge_no": -0.0056,
      "kelly_yes": 0.3,
      "kelly_no": null,
      "over_odds": 1438,
      "under_odds": -1438,
      "best_side": "YES",
      "best_ev": 0.0864,
      "best_edge": 0.0056,
      "best_odds": 1438,
      "best_p": 0.0706,
      "best_kelly_pct": 0.3,
      "flagged": true
    },
    {
      "pitcher_id": 6032,
      "pitcher_name": "Anthony Kay",
      "pitcher_team": "Chicago White Sox",
      "book": "kalshi",
      "line": 5.5,
      "threshold": 6,
      "predicted_mu": 4.16,
      "p_yes": 0.2472,
      "p_no": 0.7528,
      "ev_yes": -0.1892,
      "ev_no": 0.083,
      "edge_yes": -0.0577,
      "edge_no": 0.0577,
      "kelly_yes": null,
      "kelly_no": 5.0,
      "over_odds": 228,
      "under_odds": -228,
      "best_side": "NO",
      "best_ev": 0.083,
      "best_edge": 0.0577,
      "best_odds": -228,
      "best_p": 0.7528,
      "best_kelly_pct": 5.0,
      "flagged": true
    },
    {
      "pitcher_id": 656,
      "pitcher_name": "Javier Assad",
      "pitcher_team": "Chicago Cubs",
      "book": "kalshi",
      "line": 6.5,
      "threshold": 7,
      "predicted_mu": 3.11,
      "p_yes": 0.0455,
      "p_no": 0.9545,
      "ev_yes": -0.6042,
      "ev_no": 0.0785,
      "edge_yes": -0.0694,
      "edge_no": 0.0694,
      "kelly_yes": null,
      "kelly_no": 5.0,
      "over_odds": 770,
      "under_odds": -770,
      "best_side": "NO",
      "best_ev": 0.0785,
      "best_edge": 0.0694,
      "best_odds": -770,
      "best_p": 0.9545,
      "best_kelly_pct": 5.0,
      "flagged": true
    },
    {
      "pitcher_id": 418,
      "pitcher_name": "George Kirby",
      "pitcher_team": "Seattle Mariners",
      "book": "kalshi",
      "line": 8.5,
      "threshold": 9,
      "predicted_mu": 5.06,
      "p_yes": 0.0832,
      "p_no": 0.9168,
      "ev_yes": -0.4447,
      "ev_no": 0.0784,
      "edge_yes": -0.0667,
      "edge_no": 0.0667,
      "kelly_yes": null,
      "kelly_no": 5.0,
      "over_odds": 567,
      "under_odds": -567,
      "best_side": "NO",
      "best_ev": 0.0784,
      "best_edge": 0.0667,
      "best_odds": -567,
      "best_p": 0.9168,
      "best_kelly_pct": 5.0,
      "flagged": true
    },
    {
      "pitcher_id": 4941190,
      "pitcher_name": "JR Ritchie",
      "pitcher_team": "Atlanta Braves",
      "book": "kalshi",
      "line": 2.5,
      "threshold": 3,
      "predicted_mu": 4.42,
      "p_yes": 0.8029,
      "p_no": 0.1971,
      "ev_yes": 0.0779,
      "ev_no": -0.2275,
      "edge_yes": 0.058,
      "edge_no": -0.058,
      "kelly_yes": 5.0,
      "kelly_no": null,
      "over_odds": -292,
      "under_odds": 292,
      "best_side": "YES",
      "best_ev": 0.0779,
      "best_edge": 0.058,
      "best_odds": -292,
      "best_p": 0.8029,
      "best_kelly_pct": 5.0,
      "flagged": true
    },
    {
      "pitcher_id": 4787743,
      "pitcher_name": "Jake Bennett",
      "pitcher_team": "Boston Red Sox",
      "book": "kalshi",
      "line": 2.5,
      "threshold": 3,
      "predicted_mu": 3.43,
      "p_yes": 0.6557,
      "p_no": 0.3443,
      "ev_yes": 0.0654,
      "ev_no": -0.1047,
      "edge_yes": 0.0403,
      "edge_no": -0.0403,
      "kelly_yes": 5.0,
      "kelly_no": null,
      "over_odds": -160,
      "under_odds": 160,
      "best_side": "YES",
      "best_ev": 0.0654,
      "best_edge": 0.0403,
      "best_odds": -160,
      "best_p": 0.6557,
      "best_kelly_pct": 5.0,
      "flagged": true
    },
    {
      "pitcher_id": 1490,
      "pitcher_name": "Kyle Bradish",
      "pitcher_team": "Baltimore Orioles",
      "book": "kalshi",
      "line": 5.5,
      "threshold": 6,
      "predicted_mu": 5.22,
      "p_yes": 0.4197,
      "p_no": 0.5803,
      "ev_yes": -0.0556,
      "ev_no": 0.0445,
      "edge_yes": -0.0247,
      "edge_no": 0.0247,
      "kelly_yes": null,
      "kelly_no": 2.78,
      "over_odds": 125,
      "under_odds": -125,
      "best_side": "NO",
      "best_ev": 0.0445,
      "best_edge": 0.0247,
      "best_odds": -125,
      "best_p": 0.5803,
      "best_kelly_pct": 2.78,
      "flagged": true
    },
    {
      "pitcher_id": 656,
      "pitcher_name": "Javier Assad",
      "pitcher_team": "Chicago Cubs",
      "book": "kalshi",
      "line": 7.5,
      "threshold": 8,
      "predicted_mu": 3.11,
      "p_yes": 0.0182,
      "p_no": 0.9818,
      "ev_yes": -0.6959,
      "ev_no": 0.0444,
      "edge_yes": -0.0417,
      "edge_no": 0.0417,
      "kelly_yes": null,
      "kelly_no": 5.0,
      "over_odds": 1567,
      "under_odds": -1567,
      "best_side": "NO",
      "best_ev": 0.0444,
      "best_edge": 0.0417,
      "best_odds": -1567,
      "best_p": 0.9818,
      "best_kelly_pct": 5.0,
      "flagged": true
    },
    {
      "pitcher_id": 1055,
      "pitcher_name": "Aaron Civale",
      "pitcher_team": "Oakland Athletics",
      "book": "kalshi",
      "line": 2.5,
      "threshold": 3,
      "predicted_mu": 3.7,
      "p_yes": 0.702,
      "p_no": 0.298,
      "ev_yes": 0.0394,
      "ev_no": -0.082,
      "edge_yes": 0.0266,
      "edge_no": -0.0266,
      "kelly_yes": 4.1,
      "kelly_no": null,
      "over_odds": -208,
      "under_odds": 208,
      "best_side": "YES",
      "best_ev": 0.0394,
      "best_edge": 0.0266,
      "best_odds": -208,
      "best_p": 0.702,
      "best_kelly_pct": 4.1,
      "flagged": true
    },
    {
      "pitcher_id": 3315628,
      "pitcher_name": "Brandon Sproat",
      "pitcher_team": "Milwaukee Brewers",
      "book": "kalshi",
      "line": 6.5,
      "threshold": 7,
      "predicted_mu": 4.47,
      "p_yes": 0.1742,
      "p_no": 0.8258,
      "ev_yes": -0.1498,
      "ev_no": 0.0386,
      "edge_yes": -0.0307,
      "edge_no": 0.0307,
      "kelly_yes": null,
      "kelly_no": 5.0,
      "over_odds": 388,
      "under_odds": -388,
      "best_side": "NO",
      "best_ev": 0.0386,
      "best_edge": 0.0307,
      "best_odds": -388,
      "best_p": 0.8258,
      "best_kelly_pct": 5.0,
      "flagged": true
    },
    {
      "pitcher_id": 543,
      "pitcher_name": "Braxton Ashcraft",
      "pitcher_team": "Pittsburgh Pirates",
      "book": "kalshi",
      "line": 5.5,
      "threshold": 6,
      "predicted_mu": 5.66,
      "p_yes": 0.4918,
      "p_no": 0.5082,
      "ev_yes": 0.0378,
      "ev_no": -0.034,
      "edge_yes": 0.0179,
      "edge_no": -0.0179,
      "kelly_yes": 1.7,
      "kelly_no": null,
      "over_odds": 111,
      "under_odds": -111,
      "best_side": "YES",
      "best_ev": 0.0378,
      "best_edge": 0.0179,
      "best_odds": 111,
      "best_p": 0.4918,
      "best_kelly_pct": 1.7,
      "flagged": true
    },
    {
      "pitcher_id": 4941190,
      "pitcher_name": "JR Ritchie",
      "pitcher_team": "Atlanta Braves",
      "book": "kalshi",
      "line": 1.5,
      "threshold": 2,
      "predicted_mu": 4.42,
      "p_yes": 0.9253,
      "p_no": 0.0747,
      "ev_yes": 0.0339,
      "ev_no": -0.2885,
      "edge_yes": 0.0303,
      "edge_no": -0.0303,
      "kelly_yes": 5.0,
      "kelly_no": null,
      "over_odds": -852,
      "under_odds": 852,
      "best_side": "YES",
      "best_ev": 0.0339,
      "best_edge": 0.0303,
      "best_odds": -852,
      "best_p": 0.9253,
      "best_kelly_pct": 5.0,
      "flagged": true
    },
    {
      "pitcher_id": 4787743,
      "pitcher_name": "Jake Bennett",
      "pitcher_team": "Boston Red Sox",
      "book": "kalshi",
      "line": 1.5,
      "threshold": 2,
      "predicted_mu": 3.43,
      "p_yes": 0.8459,
      "p_no": 0.1541,
      "ev_yes": 0.0314,
      "ev_no": -0.143,
      "edge_yes": 0.0257,
      "edge_no": -0.0257,
      "kelly_yes": 5.0,
      "kelly_no": null,
      "over_odds": -456,
      "under_odds": 456,
      "best_side": "YES",
      "best_ev": 0.0314,
      "best_edge": 0.0257,
      "best_odds": -456,
      "best_p": 0.8459,
      "best_kelly_pct": 5.0,
      "flagged": true
    },
    {
      "pitcher_id": 418,
      "pitcher_name": "George Kirby",
      "pitcher_team": "Seattle Mariners",
      "book": "kalshi",
      "line": 9.5,
      "threshold": 10,
      "predicted_mu": 5.06,
      "p_yes": 0.0428,
      "p_no": 0.9572,
      "ev_yes": -0.3878,
      "ev_no": 0.0292,
      "edge_yes": -0.0271,
      "edge_no": 0.0271,
      "kelly_yes": null,
      "kelly_no": 5.0,
      "over_odds": 1329,
      "under_odds": -1329,
      "best_side": "NO",
      "best_ev": 0.0292,
      "best_edge": 0.0271,
      "best_odds": -1329,
      "best_p": 0.9572,
      "best_kelly_pct": 5.0,
      "flagged": true
    },
    {
      "pitcher_id": 543,
      "pitcher_name": "Braxton Ashcraft",
      "pitcher_team": "Pittsburgh Pirates",
      "book": "kalshi",
      "line": 4.5,
      "threshold": 5,
      "predicted_mu": 5.66,
      "p_yes": 0.6517,
      "p_no": 0.3483,
      "ev_yes": -0.0124,
      "ev_no": 0.024,
      "edge_yes": -0.0082,
      "edge_no": 0.0082,
      "kelly_yes": null,
      "kelly_no": 0.62,
      "over_odds": -194,
      "under_odds": 194,
      "best_side": "NO",
      "best_ev": 0.024,
      "best_edge": 0.0082,
      "best_odds": 194,
      "best_p": 0.3483,
      "best_kelly_pct": 0.62,
      "flagged": true
    },
    {
      "pitcher_id": 879,
      "pitcher_name": "Gavin Williams",
      "pitcher_team": "Cleveland Guardians",
      "book": "kalshi",
      "line": 7.5,
      "threshold": 8,
      "predicted_mu": 6.54,
      "p_yes": 0.3376,
      "p_no": 0.6624,
      "ev_yes": 0.0229,
      "ev_no": -0.0113,
      "edge_yes": 0.0076,
      "edge_no": -0.0076,
      "kelly_yes": 0.56,
      "kelly_no": null,
      "over_odds": 203,
      "under_odds": -203,
      "best_side": "YES",
      "best_ev": 0.0229,
      "best_edge": 0.0076,
      "best_odds": 203,
      "best_p": 0.3376,
      "best_kelly_pct": 0.56,
      "flagged": true
    },
    {
      "pitcher_id": 1490,
      "pitcher_name": "Kyle Bradish",
      "pitcher_team": "Baltimore Orioles",
      "book": "kalshi",
      "line": 7.5,
      "threshold": 8,
      "predicted_mu": 5.22,
      "p_yes": 0.1686,
      "p_no": 0.8314,
      "ev_yes": 0.0219,
      "ev_no": -0.0043,
      "edge_yes": 0.0036,
      "edge_no": -0.0036,
      "kelly_yes": 0.22,
      "kelly_no": null,
      "over_odds": 506,
      "under_odds": -506,
      "best_side": "YES",
      "best_ev": 0.0219,
      "best_edge": 0.0036,
      "best_odds": 506,
      "best_p": 0.1686,
      "best_kelly_pct": 0.22,
      "flagged": true
    },
    {
      "pitcher_id": 6032,
      "pitcher_name": "Anthony Kay",
      "pitcher_team": "Chicago White Sox",
      "book": "kalshi",
      "line": 6.5,
      "threshold": 7,
      "predicted_mu": 4.16,
      "p_yes": 0.1381,
      "p_no": 0.8619,
      "ev_yes": -0.1091,
      "ev_no": 0.02,
      "edge_yes": -0.0169,
      "edge_no": 0.0169,
      "kelly_yes": null,
      "kelly_no": 5.0,
      "over_odds": 545,
      "under_odds": -545,
      "best_side": "NO",
      "best_ev": 0.02,
      "best_edge": 0.0169,
      "best_odds": -545,
      "best_p": 0.8619,
      "best_kelly_pct": 5.0,
      "flagged": true
    },
    {
      "pitcher_id": 1490,
      "pitcher_name": "Kyle Bradish",
      "pitcher_team": "Baltimore Orioles",
      "book": "kalshi",
      "line": 6.5,
      "threshold": 7,
      "predicted_mu": 5.22,
      "p_yes": 0.2769,
      "p_no": 0.7231,
      "ev_yes": -0.0447,
      "ev_no": 0.0183,
      "edge_yes": -0.013,
      "edge_no": 0.013,
      "kelly_yes": null,
      "kelly_no": 2.24,
      "over_odds": 245,
      "under_odds": -245,
      "best_side": "NO",
      "best_ev": 0.0183,
      "best_edge": 0.013,
      "best_odds": -245,
      "best_p": 0.7231,
      "best_kelly_pct": 2.24,
      "flagged": true
    },
    {
      "pitcher_id": 1055,
      "pitcher_name": "Aaron Civale",
      "pitcher_team": "Oakland Athletics",
      "book": "kalshi",
      "line": 1.5,
      "threshold": 2,
      "predicted_mu": 3.7,
      "p_yes": 0.8728,
      "p_no": 0.1272,
      "ev_yes": 0.0149,
      "ev_no": -0.0918,
      "edge_yes": 0.0129,
      "edge_no": -0.0129,
      "kelly_yes": 4.59,
      "kelly_no": null,
      "over_odds": -614,
      "under_odds": 614,
      "best_side": "YES",
      "best_ev": 0.0149,
      "best_edge": 0.0129,
      "best_odds": -614,
      "best_p": 0.8728,
      "best_kelly_pct": 4.59,
      "flagged": true
    },
    {
      "pitcher_id": 543,
      "pitcher_name": "Braxton Ashcraft",
      "pitcher_team": "Pittsburgh Pirates",
      "book": "kalshi",
      "line": 2.5,
      "threshold": 3,
      "predicted_mu": 5.66,
      "p_yes": 0.9075,
      "p_no": 0.0925,
      "ev_yes": 0.0027,
      "ev_no": -0.0261,
      "edge_yes": 0.0025,
      "edge_no": -0.0025,
      "kelly_yes": 1.3,
      "kelly_no": null,
      "over_odds": -953,
      "under_odds": 953,
      "best_side": "YES",
      "best_ev": 0.0027,
      "best_edge": 0.0025,
      "best_odds": -953,
      "best_p": 0.9075,
      "best_kelly_pct": 1.3,
      "flagged": true
    },
    {
      "pitcher_id": 879,
      "pitcher_name": "Gavin Williams",
      "pitcher_team": "Cleveland Guardians",
      "book": "kalshi",
      "line": 6.5,
      "threshold": 7,
      "predicted_mu": 6.54,
      "p_yes": 0.4735,
      "p_no": 0.5265,
      "ev_yes": -0.0009,
      "ev_no": 0.0008,
      "edge_yes": -0.0004,
      "edge_no": 0.0004,
      "kelly_yes": null,
      "kelly_no": 0.05,
      "over_odds": 111,
      "under_odds": -111,
      "best_side": "NO",
      "best_ev": 0.0008,
      "best_edge": 0.0004,
      "best_odds": -111,
      "best_p": 0.5265,
      "best_kelly_pct": 0.05,
      "flagged": true
    },
    {
      "pitcher_id": 3315628,
      "pitcher_name": "Brandon Sproat",
      "pitcher_team": "Milwaukee Brewers",
      "book": "kalshi",
      "line": 7.5,
      "threshold": 8,
      "predicted_mu": 4.47,
      "p_yes": 0.0942,
      "p_no": 0.9058,
      "ev_yes": -0.0081,
      "ev_no": 0.0008,
      "edge_yes": -0.0008,
      "edge_no": 0.0008,
      "kelly_yes": null,
      "kelly_no": 0.4,
      "over_odds": 953,
      "under_odds": -953,
      "best_side": "NO",
      "best_ev": 0.0008,
      "best_edge": 0.0008,
      "best_odds": -953,
      "best_p": 0.9058,
      "best_kelly_pct": 0.4,
      "flagged": true
    }
  ],
  "flagged": 67
}